topsis_Vihaan_102303658/__init__.py
topsis_Vihaan_102303658/topsis.py
topsis_vihaan_102303658-1.1.1.dist-info/METADATA
topsis_vihaan_102303658-1.1.1.dist-info/WHEEL
topsis_vihaan_102303658-1.1.1.dist-info/entry_points.txt
topsis_vihaan_102303658-1.1.1.dist-info/top_level.txt
topsis_vihaan_102303658-1.1.1.dist-info/RECORD
